Metadata-Version: 2.1
Name: pycirchdl
Version: 1.1
Summary: Python logic circuit hardware description language
Home-page: https://www.samyzaf.com/pycirc/pycirchdl.html
Author: Samy Zafrany
Author-email: sz@samyzaf.com
License: MIT
Keywords: digital circuit logic hardware description modeling simulation
Platform: UNKNOWN
